{
    "latencies": {
        "total": 70553123006,
        "mean": 201580351,
        "1th": 160568706,
        "5th": 161490527,
        "10th": 162866863,
        "25th": 176859800,
        "50th": 204901547,
        "75th": 226609398,
        "90th": 229119639,
        "95th": 230422491,
        "99th": 233027305,
        "max": 235558760,
        "min": 159928212
    },
    "bytes_in": {
        "total": 27300,
        "mean": 78
    },
    "bytes_out": {
        "total": 0,
        "mean": 0
    },
    "earliest": "2024-10-20T18:47:57.656231168+09:00",
    "latest": "2024-10-20T18:52:56.798840659+09:00",
    "end": "2024-10-20T18:52:56.990147735+09:00",
    "duration": 299142609491,
    "wait": 191307076,
    "requests": 350,
    "rate": 1.1700105197167845,
    "throughput": 1.1692627551668018,
    "cpu_Utilization": 32.2,
    "success": 1,
    "status_codes": {
        "200": 350
    },
    "errors": []
}