{
    "latencies": {
        "total": 37588603399,
        "mean": 187943016,
        "1th": 185982761,
        "5th": 186326096,
        "10th": 186537775,
        "25th": 187067558,
        "50th": 187750902,
        "75th": 188702392,
        "90th": 189668449,
        "95th": 190053666,
        "99th": 191250145,
        "max": 192812684,
        "min": 185608374
    },
    "bytes_in": {
        "total": 15600,
        "mean": 78
    },
    "bytes_out": {
        "total": 0,
        "mean": 0
    },
    "earliest": "2024-10-20T18:32:57.698865253+09:00",
    "latest": "2024-10-20T18:37:56.198720078+09:00",
    "end": "2024-10-20T18:37:56.385298775+09:00",
    "duration": 298499854825,
    "wait": 186578697,
    "requests": 200,
    "rate": 0.6700170762804993,
    "throughput": 0.6695985406557436,
    "cpu_Utilization": 19,
    "success": 1,
    "status_codes": {
        "200": 200
    },
    "errors": []
}