{
    "latencies": {
        "total": 2049793195582,
        "mean": 819917278,
        "1th": 167477730,
        "5th": 213976655,
        "10th": 250852276,
        "25th": 377630159,
        "50th": 625607634,
        "75th": 1027914712,
        "90th": 1665988813,
        "95th": 2094321324,
        "99th": 3099792035,
        "max": 5876628544,
        "min": 159792548
    },
    "bytes_in": {
        "total": 417418,
        "mean": 166.9672
    },
    "bytes_out": {
        "total": 0,
        "mean": 0
    },
    "earliest": "2024-10-23T15:28:03.548809853+09:00",
    "latest": "2024-10-23T15:33:03.42903179+09:00",
    "end": "2024-10-23T15:33:03.909681455+09:00",
    "duration": 299880221937,
    "wait": 480649665,
    "requests": 2500,
    "rate": 8.336661830686552,
    "throughput": 8.316662508923706,
    "success": 0.9992,
    "status_codes": {
        "200": 2498,
        "500": 2
    },
    "errors": [
        "500 Internal Server Error"
    ]
}